setup.py
ujson_drf/__init__.py
ujson_drf/parsers.py
ujson_drf/renderers.py
ujson_drf.egg-info/PKG-INFO
ujson_drf.egg-info/SOURCES.txt
ujson_drf.egg-info/dependency_links.txt
ujson_drf.egg-info/not-zip-safe
ujson_drf.egg-info/requires.txt
ujson_drf.egg-info/top_level.txt