Metadata-Version: 1.1
Name: ujson-drf
Version: 0.2
Summary: JSON Renderer and Parser for Django Rest Framework using the ultra fast json (in C).
Home-page: https://github.com/akshaysharma096/ujson_drf
Author: Akshay Sharma
Author-email: mailbag.akshay@gmail.com
License: MIT
Keywords: django djangorestframework restframework djangorest parser renderer
Platform: UNKNOWN
Classifier: Framework :: Django
Classifier: Programming Language :: Python
Classifier: Intended Audience :: Developers
Classifier: Topic :: Software Development :: Libraries :: Python Modules
